pyroll/stationary_thermal_analysis_work_roll/__init__.py
pyroll/stationary_thermal_analysis_work_roll/report.py
pyroll/stationary_thermal_analysis_work_roll/roll.py
pyroll/stationary_thermal_analysis_work_roll/roll_pass.py
pyroll/stationary_thermal_analysis_work_roll/stationary_heat_analysis.py
pyroll_stationary_thermal_analysis_work_roll-3.0.1.dist-info/METADATA
pyroll_stationary_thermal_analysis_work_roll-3.0.1.dist-info/WHEEL
pyroll_stationary_thermal_analysis_work_roll-3.0.1.dist-info/licenses/LICENSE
pyroll_stationary_thermal_analysis_work_roll-3.0.1.dist-info/RECORD
