Metadata-Version: 2.4
Name: pyroll-stationary-thermal-analysis-work-roll
Version: 3.0.1
Summary: Plugin for PyRolL providing a model to coduct a stationary heat analysis of the used work roll.
Project-URL: Homepage, https://pyroll.readthedocs.io
Project-URL: Repository, https://github.com/pyroll-project/pyroll-stationary-thermal-analysis-work-roll
Project-URL: Documentation, https://github.com/pyroll-project/pyroll-stationary-thermal-analysis-work-roll/blob/main/docs/docs.pdf
Author-email: Christoph Renzing <christoph.renzing@imf.tu-freiberg.de>
License-Expression: BSD-3-Clause
License-File: LICENSE
Classifier: Development Status :: 5 - Production/Stable
Classifier: Framework :: Hatch
Classifier: Framework :: IPython
Classifier: Framework :: Jupyter
Classifier: Framework :: Pytest
Classifier: Framework :: Sphinx
Classifier: Intended Audience :: Manufacturing
Classifier: Intended Audience :: Science/Research
Classifier: License :: OSI Approved :: BSD License
Classifier: Natural Language :: English
Classifier: Operating System :: OS Independent
Classifier: Programming Language :: Python :: 3
Classifier: Programming Language :: Python :: 3.9
Classifier: Programming Language :: Python :: 3.10
Classifier: Programming Language :: Python :: 3.11
Classifier: Topic :: Scientific/Engineering
Requires-Python: <4.0,>=3.9
Requires-Dist: matplotlib
Requires-Dist: mpmath
Requires-Dist: pyroll-core~=3.0
Requires-Dist: pyroll-report~=3.0
